batem/propertiesDB.xlsx
batem/try_elasticity.py
batem/core/__init__.py
batem/core/building.py
batem/core/cbr.py
batem/core/climate.py
batem/core/comfort.py
batem/core/components.py
batem/core/control.py
batem/core/data.py
batem/core/dataloader.py
batem/core/fem2D.py
batem/core/flexible.py
batem/core/inhabitants.py
batem/core/lambdahouse.py
batem/core/library.py
batem/core/linreg.py
batem/core/model.py
batem/core/nlreg.py
batem/core/solar.py
batem/core/statemodel.py
batem/core/system.py
batem/core/thermal.py
batem/core/timemg.py
batem/core/utils.py
batem/core/weather.py
batem/ecommunity/__init__.py
batem/ecommunity/adaptive.py
batem/ecommunity/basic.py
batem/ecommunity/color.py
batem/ecommunity/dynamic.py
batem/ecommunity/indicators.py
batem/ecommunity/irise.py
batem/ecommunity/nosignal.py
batem/ecommunity/reactadapt.py
batem/ecommunity/reactive.py
batem/ecommunity/shift.py
batem/ecommunity/simulator.py
batem/graphs/utils.py
batem/graphs/directed/main.py
batem/graphs/heatpumps/__init__.py
batem/graphs/heatpumps/hp_dashboard.py
batem/graphs/heatpumps/parameters.py
batem/graphs/heatpumps/run_dashboard.py
batem/graphs/heatpumps/simulation.py
batem/graphs/heatpumps/variables.py
batem/graphs/heatpumps/models/HeatPumpBase.py
batem/graphs/heatpumps/models/HeatPumpCascade.py
batem/graphs/heatpumps/models/HeatPumpCascade2IHX.py
batem/graphs/heatpumps/models/HeatPumpCascade2IHXTrans.py
batem/graphs/heatpumps/models/HeatPumpCascadeBase.py
batem/graphs/heatpumps/models/HeatPumpCascadeEcon.py
batem/graphs/heatpumps/models/HeatPumpCascadeEconIHX.py
batem/graphs/heatpumps/models/HeatPumpCascadeEconIHXTrans.py
batem/graphs/heatpumps/models/HeatPumpCascadeEconTrans.py
batem/graphs/heatpumps/models/HeatPumpCascadeFlash.py
batem/graphs/heatpumps/models/HeatPumpCascadeFlashTrans.py
batem/graphs/heatpumps/models/HeatPumpCascadeIC.py
batem/graphs/heatpumps/models/HeatPumpCascadeICTrans.py
batem/graphs/heatpumps/models/HeatPumpCascadeIHXEcon.py
batem-0.3.1.dist-info/licenses/LICENSE
batem-0.3.1.dist-info/METADATA
batem-0.3.1.dist-info/WHEEL
batem-0.3.1.dist-info/top_level.txt
batem-0.3.1.dist-info/RECORD
