Metadata-Version: 2.4
Name: batem
Version: 0.3.1
Summary: A meta-package including core, heatpump, tespy, reno, sites and ecommunity
Author-email: Stephane Ploix <stephane.ploix@grenoble-inp.fr>
License-Expression: MIT
Project-URL: Homepage, https://gricad-gitlab.univ-grenoble-alpes.fr/batem/batem_all
Requires-Python: >=3.10
License-File: LICENSE
Requires-Dist: ipython
Requires-Dist: ipywidgets
Requires-Dist: nbformat
Requires-Dist: joblib
Requires-Dist: matplotlib
Requires-Dist: networkx
Requires-Dist: numpy
Requires-Dist: nbformat
Requires-Dist: openpyxl
Requires-Dist: pandas
Requires-Dist: plotly
Requires-Dist: prettytable
Requires-Dist: psychrochart
Requires-Dist: PyExcelerate
Requires-Dist: importlib-metadata
Requires-Dist: pymor
Requires-Dist: pytz
Requires-Dist: Requests
Requires-Dist: SALib
Requires-Dist: hplib
Requires-Dist: scipy
Requires-Dist: SQLAlchemy
Requires-Dist: tzlocal
Requires-Dist: tomlkit
Requires-Dist: timezonefinder>=8.0
Requires-Dist: windrose
Requires-Dist: kaleido
Requires-Dist: ipympl
Requires-Dist: weasyprint
Requires-Dist: CoolProp
Requires-Dist: db-sqlite3
Requires-Dist: pydantic==2.10
Requires-Dist: tzlocal
Requires-Dist: pandas
Requires-Dist: snakeviz
Requires-Dist: CoolProp
Requires-Dist: tespy
Requires-Dist: scikit-learn
Requires-Dist: pypandoc
Requires-Dist: pvlib
Requires-Dist: pyvista
Requires-Dist: pyvista[jupyter]
Requires-Dist: trame
Requires-Dist: trame-vtk
Requires-Dist: trame-plotly
Requires-Dist: geopy
Requires-Dist: contourpy
Requires-Dist: z3-solver
Dynamic: license-file
